MANIFEST.in
README.rst
setup.py
tests/__init__.py
tests/model_meta.py
tests/test_sautil.py
tests/test_tagging.py
tests/test_tags.py
tgext/__init__.py
tgext.tagging.egg-info/PKG-INFO
tgext.tagging.egg-info/SOURCES.txt
tgext.tagging.egg-info/dependency_links.txt
tgext.tagging.egg-info/entry_points.txt
tgext.tagging.egg-info/namespace_packages.txt
tgext.tagging.egg-info/not-zip-safe
tgext.tagging.egg-info/requires.txt
tgext.tagging.egg-info/top_level.txt
tgext/tagging/__init__.py
tgext/tagging/controllers/__init__.py
tgext/tagging/controllers/controller.py
tgext/tagging/model/__init__.py
tgext/tagging/model/app_auth.py
tgext/tagging/model/metadata.py
tgext/tagging/model/sautils.py
tgext/tagging/model/setup.py
tgext/tagging/model/tagging.py
tgext/tagging/static/__init__.py
tgext/tagging/static/__init__.pyc
tgext/tagging/static/delete.png
tgext/tagging/static/tagging.css
tgext/tagging/static/tagging.js
tgext/tagging/templates/__init__.py
tgext/tagging/templates/search.html
tgext/tagging/templates/tagcloud.html
tgext/tagging/templates/taglist.html
tgext/tagging/templates/tags.html
tgext/tagging/widgets/__init__.py
tgext/tagging/widgets/tagcloud.py
tgext/tagging/widgets/taglist.py
tgext/tagging/widgets/tw_compat.py