Metadata-Version: 1.1
Name: tgext.tagging
Version: 0.3.0
Summary: Tagging support for TurboGears2 applications
Home-page: http://bitbucket.org/_amol_/tgext.tagging
Author: Alessandro Molina
Author-email: alessandro.molina@axant.it
License: MIT
Keywords: turbogears2.extension
Platform: UNKNOWN
Classifier: Environment :: Web Environment
Classifier: Topic :: Software Development :: Libraries :: Python Modules
Classifier: Framework :: TurboGears
